{"nodes": [{"id": "qa_sprint2_search_png_qa_sprint2_search", "label": "Sprint 2 Search \u2014 Specialty/location/insurance search filters", "file_type": "image", "source_file": "qa-sprint2-search.png", "source_location": null, "source_url": null, "captured_at": "2026-07-04T13:03:00", "author": null, "contributor": null}], "edges": [{"source": "qa_sprint2_search_png_qa_sprint2_search", "target": "sprint_2", "relation": "conceptually_related_to", "confidence": "INFERRED", "confidence_score": 0.95, "source_file": "qa-sprint2-search.png", "source_location": null, "weight": 1.0}], "hyperedges": []}